{
  "Units": [
    {
      "Id": 1,
      "Race": "Człowiek",
      "PrimaryWeaponId": 3,
      "WW": 20,
      "US": 20,
      "K": 20,
      "Odp": 20,
      "Zr": 20,
      "Int": 20,
      "SW": 20,
      "Ogd": 20,
      "A": 1,
      "Sz": 4,
      "MaxHealth": 10
    },
    {
      "Id": 2,
      "Race": "Elf",
      "PrimaryWeaponId": 3,
      "WW": 20,
      "US": 30,
      "K": 20,
      "Odp": 20,
      "Zr": 30,
      "Int": 20,
      "SW": 20,
      "Ogd": 20,
      "A": 1,
      "Sz": 5,
      "MaxHealth": 9
    },
    {
      "Id": 3,
      "Race": "Krasnolud",
      "PrimaryWeaponId": 3,
      "WW": 30,
      "US": 20,
      "K": 20,
      "Odp": 30,
      "Zr": 10,
      "Int": 20,
      "SW": 20,
      "Ogd": 10,
      "A": 1,
      "Sz": 3,
      "MaxHealth": 11,
      "StoutHearted": true
    },
    {
      "Id": 4,
      "Race": "Niziołek",
      "PrimaryWeaponId": 3,
      "WW": 10,
      "US": 30,
      "K": 10,
      "Odp": 10,
      "Zr": 30,
      "Int": 20,
      "SW": 20,
      "Ogd": 30,
      "A": 1,
      "Sz": 4,
      "MaxHealth": 8
    },
    {
      "Id": 5,
      "Race": "Ork",
      "PrimaryWeaponId": 3,
      "WW": 50,
      "US": 20,
      "K": 40,
      "Odp": 50,
      "Zr": 20,
      "Int": 10,
      "SW": 30,
      "Ogd": 10,
      "A": 3,
      "Sz": 4,
      "MaxHealth": 15,
      "Armor_head": 1,
      "Armor_arms": 0,
      "Armor_torso": 0,
      "Armor_legs": 0
    },
    {
      "Id": 6,
      "Race": "Skaven",
      "PrimaryWeaponId": 3,
      "WW": 25,
      "US": 35,
      "K": 20,
      "Odp": 30,
      "Zr": 50,
      "Int": 30,
      "SW": 30,
      "Ogd": 20,
      "A": 1,
      "Sz": 5,
      "MaxHealth": 10,
      "Armor_head": 1,
      "Armor_arms": 0,
      "Armor_torso": 0,
      "Armor_legs": 0,
      "Dodge": 1
    },
    {
      "Id": 7,
      "Race": "Smok",
      "PrimaryWeaponId": 5,
      "WW": 90,
      "US": 0,
      "K": 60,
      "Odp": 60,
      "Zr": 60,
      "Int": 80,
      "SW": 90,
      "Ogd": 60,
      "A": 5,
      "Sz": 6,
      "MaxHealth": 60,
      "Armor_head": 3,
      "Armor_arms": 3,
      "Armor_torso": 3,
      "Armor_legs": 3,
      "PowerfulBlow": true,
      "Terryfying": true
    },
    {
      "Id": 8,
      "Race": "Troll",
      "PrimaryWeaponId": 2,
      "WW": 40,
      "US": 0,
      "K": 50,
      "Odp": 50,
      "Zr": 20,
      "Int": 10,
      "SW": 20,
      "Ogd": 10,
      "A": 3,
      "Sz": 6,
      "MaxHealth": 30,
      "Armor_head": 0,
      "Armor_arms": 0,
      "Armor_torso": 0,
      "Armor_legs": 0,
      "Frightening": true,
      "PowerfulBlow": true
    },
    {
      "Id": 9,
      "Race": "Wilk",
      "PrimaryWeaponId": 4,
      "WW": 40,
      "US": 0,
      "K": 30,
      "Odp": 30,
      "Zr": 50,
      "Int": 20,
      "SW": 20,
      "Ogd": 10,
      "A": 1,
      "Sz": 6,
      "MaxHealth": 11,
      "Armor_head": 0,
      "Armor_arms": 0,
      "Armor_torso": 0,
      "Armor_legs": 0
    }
  ]
}
